common/__init__.py
common/constants.py
skyeye/__init__.py
skyeye/web/__init__.py
skyeye/web/middleware/__init__.py
skyeye/web/middleware/fastapi.py
skyeye/web/middleware/otel.py
self_python_instr-0.1.3.dist-info/METADATA
self_python_instr-0.1.3.dist-info/WHEEL
self_python_instr-0.1.3.dist-info/top_level.txt
self_python_instr-0.1.3.dist-info/RECORD
