Metadata-Version: 2.1
Name: self-python-instr
Version: 0.1.3
Summary: Skyeye Python FastAPI R.E.D 
Home-page: https://artifact.srdcloud.cn/artifactory/api/pypi/ctcai-oshare-pypi-mc/skyeye-python-instrumentator
Author: zr
Author-email: yihengrui1206@163.com
Requires-Dist: fastapi
Requires-Dist: starlette
